{
  "experiment": "exp125c_RG_scaling_alpha_unification",
  "hypothesis_id": "H83",
  "hypothesis": "The per-corpus 4-vector of RG-scaling exponents alpha(c) gives a unified Quran-distinctive single linear coordinate alpha_LDA_RG(c) across the 11-corpus pool, with full-pool Quran |z|>=5 AND LOO robust at min |z|_LOO>=4.",
  "verdict": "FAIL_no_alpha_unification",
  "verdict_full_pool": "FAIL_no_alpha_unification",
  "verdict_loo_robustness": "FAIL_alpha_lda_loo_overfit",
  "verdict_reason": "Full-pool: |z_quran|=2.39, max_other|z|=2.62, J=0.57. LOO: min |z_quran|=0.08, max max_other|z|=2.99.",
  "prereg_hash": "1fa0f0084a38f0b6f5a818f1bfd12076d2396fbdf569d5e1201148b65f10996e",
  "frozen_constants": {
    "EXPECTED_CORPORA": [
      "quran",
      "poetry_jahili",
      "poetry_islami",
      "poetry_abbasi",
      "hindawi",
      "ksucca",
      "arabic_bible",
      "hebrew_tanakh",
      "greek_nt",
      "pali",
      "avestan_yasna"
    ],
    "SCALES": [
      1,
      2,
      4,
      8,
      16
    ],
    "MIN_VERSES_FOR_RG": 32,
    "RG_FEATURES": [
      "EL_rate",
      "p_max",
      "H_EL",
      "VL_CV"
    ],
    "Z_QURAN_OUTLIER": 5.0,
    "Z_NO_COMPETITOR": 2.0,
    "FISHER_J_FLOOR": 5.0,
    "LOO_MIN_Z_QURAN": 4.0,
    "LOO_MAX_OTHER_ABS_Z": 2.5,
    "RIDGE_EPS": 1e-06,
    "PARTIAL_Z_FLOOR": 3.0
  },
  "results": {
    "n_qualifying_chapters": {
      "quran": 62,
      "poetry_jahili": 22,
      "poetry_islami": 96,
      "poetry_abbasi": 756,
      "hindawi": 71,
      "ksucca": 13,
      "arabic_bible": 328,
      "hebrew_tanakh": 411,
      "greek_nt": 102,
      "pali": 186,
      "avestan_yasna": 1
    },
    "per_corpus_per_scale_medians": {
      "quran": {
        "1": {
          "EL_rate": 0.7478813559322034,
          "p_max": 0.7478813559322034,
          "H_EL": 0.8900612204099703,
          "VL_CV": 0.4415510731123732
        },
        "2": {
          "EL_rate": 0.7437629937629937,
          "p_max": 0.7437629937629937,
          "H_EL": 0.8554568707466952,
          "VL_CV": 0.32683690248639996
        },
        "4": {
          "EL_rate": 0.7277777777777777,
          "p_max": 0.7277777777777777,
          "H_EL": 0.980076738160906,
          "VL_CV": 0.25287834171809453
        },
        "8": {
          "EL_rate": 0.75,
          "p_max": 0.75,
          "H_EL": 0.9184036059559461,
          "VL_CV": 0.18435803221964622
        },
        "16": {
          "EL_rate": 0.8333333333333334,
          "p_max": 0.8333333333333334,
          "H_EL": 0.6500224216483541,
          "VL_CV": 0.14009326395337893
        }
      },
      "poetry_jahili": {
        "1": {
          "EL_rate": 0.21690767519466075,
          "p_max": 0.21690767519466075,
          "H_EL": 3.374669416595674,
          "VL_CV": 0.14738746242332798
        },
        "2": {
          "EL_rate": 0.2330316742081448,
          "p_max": 0.2330316742081448,
          "H_EL": 3.1833673884324196,
          "VL_CV": 0.10023420137727274
        },
        "4": {
          "EL_rate": 0.3078947368421052,
          "p_max": 0.3078947368421052,
          "H_EL": 2.687484666478404,
          "VL_CV": 0.07027942546044885
        },
        "8": {
          "EL_rate": 0.3666666666666667,
          "p_max": 0.3666666666666667,
          "H_EL": 2.064042639445697,
          "VL_CV": 0.044281382015421415
        },
        "16": {
          "EL_rate": 0.5,
          "p_max": 0.5,
          "H_EL": 1.0,
          "VL_CV": 0.02358038293646739
        }
      },
      "poetry_islami": {
        "1": {
          "EL_rate": 0.23928352725045926,
          "p_max": 0.23928352725045926,
          "H_EL": 3.3393865982526654,
          "VL_CV": 0.14611536509708975
        },
        "2": {
          "EL_rate": 0.25,
          "p_max": 0.25,
          "H_EL": 3.0837787313833864,
          "VL_CV": 0.09878974733190041
        },
        "4": {
          "EL_rate": 0.2777777777777778,
          "p_max": 0.2777777777777778,
          "H_EL": 2.6623795055370225,
          "VL_CV": 0.06840011246166247
        },
        "8": {
          "EL_rate": 0.37797619047619047,
          "p_max": 0.37797619047619047,
          "H_EL": 2.0,
          "VL_CV": 0.049105448815322604
        },
        "16": {
          "EL_rate": 0.5,
          "p_max": 0.5,
          "H_EL": 1.0,
          "VL_CV": 0.03197132659783525
        }
      },
      "poetry_abbasi": {
        "1": {
          "EL_rate": 0.2212491738268341,
          "p_max": 0.2212491738268341,
          "H_EL": 3.3862905068221285,
          "VL_CV": 0.14958104675875586
        },
        "2": {
          "EL_rate": 0.23529411764705882,
          "p_max": 0.23529411764705882,
          "H_EL": 3.155671621918718,
          "VL_CV": 0.10290295609068954
        },
        "4": {
          "EL_rate": 0.25925925925925924,
          "p_max": 0.25925925925925924,
          "H_EL": 2.822181958642873,
          "VL_CV": 0.07302533031612608
        },
        "8": {
          "EL_rate": 0.3,
          "p_max": 0.3,
          "H_EL": 2.25,
          "VL_CV": 0.050743130591679876
        },
        "16": {
          "EL_rate": 0.5,
          "p_max": 0.5,
          "H_EL": 1.5,
          "VL_CV": 0.03318530169785355
        }
      },
      "hindawi": {
        "1": {
          "EL_rate": 0.1836734693877551,
          "p_max": 0.1836734693877551,
          "H_EL": 3.479183200312327,
          "VL_CV": 0.3927730828227358
        },
        "2": {
          "EL_rate": 0.2,
          "p_max": 0.2,
          "H_EL": 3.193269689515108,
          "VL_CV": 0.29967549465257254
        },
        "4": {
          "EL_rate": 0.25,
          "p_max": 0.25,
          "H_EL": 2.8553885422075336,
          "VL_CV": 0.20657882854867324
        },
        "8": {
          "EL_rate": 0.3333333333333333,
          "p_max": 0.3333333333333333,
          "H_EL": 2.2516291673878226,
          "VL_CV": 0.14158654403634147
        },
        "16": {
          "EL_rate": 0.3333333333333333,
          "p_max": 0.3333333333333333,
          "H_EL": 1.584962500721156,
          "VL_CV": 0.08063453507576214
        }
      },
      "ksucca": {
        "1": {
          "EL_rate": 0.22033898305084745,
          "p_max": 0.22033898305084745,
          "H_EL": 3.3213053050023884,
          "VL_CV": 1.0886715904845266
        },
        "2": {
          "EL_rate": 0.2457627118644068,
          "p_max": 0.2457627118644068,
          "H_EL": 3.132156786023467,
          "VL_CV": 0.7439578575984933
        },
        "4": {
          "EL_rate": 0.2926829268292683,
          "p_max": 0.2926829268292683,
          "H_EL": 2.958267868099842,
          "VL_CV": 0.5800602710582659
        },
        "8": {
          "EL_rate": 0.25,
          "p_max": 0.25,
          "H_EL": 2.5,
          "VL_CV": 0.39485463714440616
        },
        "16": {
          "EL_rate": 0.42857142857142855,
          "p_max": 0.42857142857142855,
          "H_EL": 2.0,
          "VL_CV": 0.263936966015557
        }
      },
      "arabic_bible": {
        "1": {
          "EL_rate": 0.2571428571428571,
          "p_max": 0.2571428571428571,
          "H_EL": 3.122963749648272,
          "VL_CV": 0.35366633930540387
        },
        "2": {
          "EL_rate": 0.2857142857142857,
          "p_max": 0.2857142857142857,
          "H_EL": 2.87052742116558,
          "VL_CV": 0.24631364572156733
        },
        "4": {
          "EL_rate": 0.3076923076923077,
          "p_max": 0.3076923076923077,
          "H_EL": 2.446439344671016,
          "VL_CV": 0.17247844137808344
        },
        "8": {
          "EL_rate": 0.4,
          "p_max": 0.4,
          "H_EL": 1.9219280948873623,
          "VL_CV": 0.12112881560086894
        },
        "16": {
          "EL_rate": 0.5,
          "p_max": 0.5,
          "H_EL": 1.0,
          "VL_CV": 0.06827303945075153
        }
      },
      "hebrew_tanakh": {
        "1": {
          "EL_rate": 0.22857142857142856,
          "p_max": 0.22857142857142856,
          "H_EL": 3.1830904844034347,
          "VL_CV": 0.08561673015949707
        },
        "2": {
          "EL_rate": 0.25,
          "p_max": 0.25,
          "H_EL": 2.952819531114783,
          "VL_CV": 0.04645197181314793
        },
        "4": {
          "EL_rate": 0.29411764705882354,
          "p_max": 0.29411764705882354,
          "H_EL": 2.5,
          "VL_CV": 0.03117776629603886
        },
        "8": {
          "EL_rate": 0.4,
          "p_max": 0.4,
          "H_EL": 1.9219280948873623,
          "VL_CV": 0.021119218934890754
        },
        "16": {
          "EL_rate": 0.5,
          "p_max": 0.5,
          "H_EL": 1.0,
          "VL_CV": 0.013579554096860996
        }
      },
      "greek_nt": {
        "1": {
          "EL_rate": 0.33045977011494254,
          "p_max": 0.33045977011494254,
          "H_EL": 2.5683199192193555,
          "VL_CV": 0.3536897792125889
        },
        "2": {
          "EL_rate": 0.3333333333333333,
          "p_max": 0.3333333333333333,
          "H_EL": 2.4891251033341133,
          "VL_CV": 0.24393211053956212
        },
        "4": {
          "EL_rate": 0.375,
          "p_max": 0.375,
          "H_EL": 2.120003152118536,
          "VL_CV": 0.17150241948194345
        },
        "8": {
          "EL_rate": 0.5,
          "p_max": 0.5,
          "H_EL": 1.5932129370439116,
          "VL_CV": 0.11966978733688952
        },
        "16": {
          "EL_rate": 0.5,
          "p_max": 0.5,
          "H_EL": 1.0,
          "VL_CV": 0.07544250757629649
        }
      },
      "pali": {
        "1": {
          "EL_rate": 0.4808201058201058,
          "p_max": 0.4808201058201058,
          "H_EL": 2.089938976016876,
          "VL_CV": 0.7754087832085503
        },
        "2": {
          "EL_rate": 0.5,
          "p_max": 0.5,
          "H_EL": 2.0886563798711233,
          "VL_CV": 0.592589373050512
        },
        "4": {
          "EL_rate": 0.5,
          "p_max": 0.5,
          "H_EL": 2.0760716690424252,
          "VL_CV": 0.45977481350672433
        },
        "8": {
          "EL_rate": 0.5133376707872479,
          "p_max": 0.5133376707872479,
          "H_EL": 1.9214846013423306,
          "VL_CV": 0.3624678531011256
        },
        "16": {
          "EL_rate": 0.5,
          "p_max": 0.5,
          "H_EL": 1.6775634273878262,
          "VL_CV": 0.2867631511823442
        }
      },
      "avestan_yasna": {
        "1": {
          "EL_rate": 0.4166666666666667,
          "p_max": 0.4166666666666667,
          "H_EL": 2.3334490587074592,
          "VL_CV": 0.9554986708333123
        },
        "2": {
          "EL_rate": 0.5,
          "p_max": 0.5,
          "H_EL": 1.945530556036326,
          "VL_CV": 0.4050151225431704
        },
        "4": {
          "EL_rate": 0.4444444444444444,
          "p_max": 0.4444444444444444,
          "H_EL": 1.836591668108979,
          "VL_CV": 0.3968982140347247
        },
        "8": {
          "EL_rate": 0.5,
          "p_max": 0.5,
          "H_EL": 1.5,
          "VL_CV": 0.16679520876266604
        },
        "16": {
          "EL_rate": 0.5,
          "p_max": 0.5,
          "H_EL": 1.0,
          "VL_CV": 0.0005310602937938772
        }
      }
    },
    "alpha_matrix": {
      "quran": {
        "EL_rate": 0.032421616827826454,
        "p_max": 0.032421616827826454,
        "H_EL": -0.08043969911522068,
        "VL_CV": -0.41384460735166906
      },
      "poetry_jahili": {
        "EL_rate": 0.30636370387666617,
        "p_max": 0.30636370387666617,
        "H_EL": -0.4134573256309506,
        "VL_CV": -0.6466512214475441
      },
      "poetry_islami": {
        "EL_rate": 0.2722781289117464,
        "p_max": 0.2722781289117464,
        "H_EL": -0.41038654976517974,
        "VL_CV": -0.5392992972294894
      },
      "poetry_abbasi": {
        "EL_rate": 0.2703009300868987,
        "p_max": 0.2703009300868987,
        "H_EL": -0.2837508576047735,
        "VL_CV": -0.5364622171319856
      },
      "hindawi": {
        "EL_rate": 0.24566102780696836,
        "p_max": 0.24566102780696836,
        "H_EL": -0.27726650402344355,
        "VL_CV": -0.5650169539715043
      },
      "ksucca": {
        "EL_rate": 0.19442838740028706,
        "p_max": 0.19442838740028706,
        "H_EL": -0.1788729028528099,
        "VL_CV": -0.5002506240712224
      },
      "arabic_bible": {
        "EL_rate": 0.24041428581755486,
        "p_max": 0.24041428581755486,
        "H_EL": -0.3864593121925433,
        "VL_CV": -0.576995650167056
      },
      "hebrew_tanakh": {
        "EL_rate": 0.2936637939002568,
        "p_max": 0.2936637939002568,
        "H_EL": -0.3960395160633539,
        "VL_CV": -0.6450096618920826
      },
      "greek_nt": {
        "EL_rate": 0.17798693905298607,
        "p_max": 0.17798693905298607,
        "H_EL": -0.33653494841864373,
        "VL_CV": -0.5485490706777735
      },
      "pali": {
        "EL_rate": 0.015084178092564352,
        "p_max": 0.015084178092564352,
        "H_EL": -0.0754540755076706,
        "VL_CV": -0.3579374556887748
      },
      "avestan_yasna": {
        "EL_rate": 0.0526068811667586,
        "p_max": 0.0526068811667586,
        "H_EL": -0.28201290830198406,
        "VL_CV": -2.2906222898363597
      }
    },
    "alpha_r2_matrix": {
      "quran": {
        "EL_rate": 0.44846510682570384,
        "p_max": 0.44846510682570384,
        "H_EL": 0.30972465051649123,
        "VL_CV": 0.9992679821867693
      },
      "poetry_jahili": {
        "EL_rate": 0.9682812436145365,
        "p_max": 0.9682812436145365,
        "H_EL": 0.8371077564144063,
        "VL_CV": 0.9855715519626062
      },
      "poetry_islami": {
        "EL_rate": 0.9098610865298561,
        "p_max": 0.9098610865298561,
        "H_EL": 0.84767104435244,
        "VL_CV": 0.9986474905783045
      },
      "poetry_abbasi": {
        "EL_rate": 0.8214759183132172,
        "p_max": 0.8214759183132172,
        "H_EL": 0.8939582625850779,
        "VL_CV": 0.9986195130998703
      },
      "hindawi": {
        "EL_rate": 0.9353868466899917,
        "p_max": 0.9353868466899917,
        "H_EL": 0.9209149874886686,
        "VL_CV": 0.9828886473418943
      },
      "ksucca": {
        "EL_rate": 0.6717013346557514,
        "p_max": 0.6717013346557514,
        "H_EL": 0.9134374936038203,
        "VL_CV": 0.9944715038114783
      },
      "arabic_bible": {
        "EL_rate": 0.9465180567994614,
        "p_max": 0.9465180567994614,
        "H_EL": 0.8576914789544228,
        "VL_CV": 0.9886353285621987
      },
      "hebrew_tanakh": {
        "EL_rate": 0.9630515388511879,
        "p_max": 0.9630515388511879,
        "H_EL": 0.8604000407851071,
        "VL_CV": 0.9920602723187384
      },
      "greek_nt": {
        "EL_rate": 0.877504542510356,
        "p_max": 0.877504542510356,
        "H_EL": 0.884744838360929,
        "VL_CV": 0.9972226713953675
      },
      "pali": {
        "EL_rate": 0.4991015931661411,
        "p_max": 0.4991015931661411,
        "H_EL": 0.7585843202854521,
        "VL_CV": 0.9991327946366934
      },
      "avestan_yasna": {
        "EL_rate": 0.45690041116787117,
        "p_max": 0.45690041116787117,
        "H_EL": 0.9130567272531055,
        "VL_CV": 0.6881897471782348
      }
    },
    "alpha_LDA_loading": {
      "EL_rate": -0.5139696411966173,
      "p_max": -0.5139696402724275,
      "H_EL": 0.2690777549330608,
      "VL_CV": 0.6318762367795101
    },
    "alpha_LDA_score_per_corpus": {
      "quran": 2.3823862842527603,
      "poetry_jahili": -1.3843210040309362,
      "poetry_islami": -0.9059833714266983,
      "poetry_abbasi": -0.5953730567837311,
      "hindawi": -0.3709359204631779,
      "ksucca": 0.4416854239800361,
      "arabic_bible": -0.5814173803378306,
      "hebrew_tanakh": -1.2164995767316493,
      "greek_nt": 0.18764944269360195,
      "pali": 2.6350700143174826,
      "avestan_yasna": -0.592260855469857
    },
    "z_quran_alpha_LDA": 2.3918718426172147,
    "abs_z_quran_alpha_LDA": 2.3918718426172147,
    "max_other_abs_z_alpha_LDA": 2.622498933165503,
    "z_per_corpus_alpha_LDA": {
      "quran": 2.3918718426172147,
      "poetry_jahili": -1.046041404196867,
      "poetry_islami": -0.6094576301683023,
      "poetry_abbasi": -0.3259603383480203,
      "hindawi": -0.12111421015709685,
      "ksucca": 0.6205738135964441,
      "arabic_bible": -0.31322284609029993,
      "hebrew_tanakh": -0.8928690274087692,
      "greek_nt": 0.3887125091758422,
      "pali": 2.622498933165503,
      "avestan_yasna": -0.323119799568434
    },
    "fisher_ratio_J_alpha_full": 0.5721050911505071,
    "unified_formula_string": "alpha_LDA_RG(c) = -0.5140 * z_alpha_EL_rate - 0.5140 * z_alpha_p_max + 0.2691 * z_alpha_H_EL + 0.6319 * z_alpha_VL_CV",
    "loo_results": [
      {
        "held_out": "poetry_jahili",
        "z_quran_lda_loo": 2.390689660824073,
        "abs_z_quran_lda_loo": 2.390689660824073,
        "max_other_abs_z_loo": 2.6167078719598487,
        "fisher_ratio_J_loo": 0.5901812890699473
      },
      {
        "held_out": "poetry_islami",
        "z_quran_lda_loo": 2.391011360318957,
        "abs_z_quran_lda_loo": 2.391011360318957,
        "max_other_abs_z_loo": 2.6123596726998595,
        "fisher_ratio_J_loo": 0.563791082465989
      },
      {
        "held_out": "poetry_abbasi",
        "z_quran_lda_loo": 2.391441221533306,
        "abs_z_quran_lda_loo": 2.391441221533306,
        "max_other_abs_z_loo": 2.615806439901179,
        "fisher_ratio_J_loo": 0.5616982238087564
      },
      {
        "held_out": "hindawi",
        "z_quran_lda_loo": 2.3899237700201192,
        "abs_z_quran_lda_loo": 2.3899237700201192,
        "max_other_abs_z_loo": 2.6071504243158263,
        "fisher_ratio_J_loo": 0.5674173322322245
      },
      {
        "held_out": "ksucca",
        "z_quran_lda_loo": 2.308767713060908,
        "abs_z_quran_lda_loo": 2.308767713060908,
        "max_other_abs_z_loo": 2.4403015084316,
        "fisher_ratio_J_loo": 0.6674698242937078
      },
      {
        "held_out": "arabic_bible",
        "z_quran_lda_loo": 2.391572442022625,
        "abs_z_quran_lda_loo": 2.391572442022625,
        "max_other_abs_z_loo": 2.6278606915099934,
        "fisher_ratio_J_loo": 0.5618218665823372
      },
      {
        "held_out": "hebrew_tanakh",
        "z_quran_lda_loo": 2.391347983037719,
        "abs_z_quran_lda_loo": 2.391347983037719,
        "max_other_abs_z_loo": 2.6198318588087206,
        "fisher_ratio_J_loo": 0.5769890932811806
      },
      {
        "held_out": "greek_nt",
        "z_quran_lda_loo": 2.355099680785745,
        "abs_z_quran_lda_loo": 2.355099680785745,
        "max_other_abs_z_loo": 2.64600251367342,
        "fisher_ratio_J_loo": 0.6177376636494221
      },
      {
        "held_out": "pali",
        "z_quran_lda_loo": 2.3771343196160792,
        "abs_z_quran_lda_loo": 2.3771343196160792,
        "max_other_abs_z_loo": 2.6468436900976977,
        "fisher_ratio_J_loo": 3.220265729008768
      },
      {
        "held_out": "avestan_yasna",
        "z_quran_lda_loo": 0.07937255703684455,
        "abs_z_quran_lda_loo": 0.07937255703684455,
        "max_other_abs_z_loo": 2.988058612936102,
        "fisher_ratio_J_loo": 0.803313628395682
      }
    ],
    "loo_min_abs_z_quran": 0.07937255703684455,
    "loo_max_other_abs_z": 2.988058612936102
  },
  "audit_report": {
    "ok": true,
    "checks": {
      "A1_n_qualifying_per_corpus": {
        "quran": 62,
        "poetry_jahili": 22,
        "poetry_islami": 96,
        "poetry_abbasi": 756,
        "hindawi": 71,
        "ksucca": 13,
        "arabic_bible": 328,
        "hebrew_tanakh": 411,
        "greek_nt": 102,
        "pali": 186,
        "avestan_yasna": 1
      },
      "A2_no_nan_alpha": true,
      "A3_low_r2_corpora": [
        {
          "corpus": "quran",
          "n_good_r2": 1
        },
        {
          "corpus": "pali",
          "n_good_r2": 2
        },
        {
          "corpus": "avestan_yasna",
          "n_good_r2": 2
        }
      ],
      "A4_S_W_nonsingular": true,
      "A5_deterministic": true
    }
  },
  "wall_time_s": 37.5613
}